futures_zero/__init__.py
futures_zero/config.py
futures_zero/futures.py
futures_zero/server.py
futures_zero/utils.py
futures_zero/worker.py
futures_zero-0.0b11.dist-info/LICENSE
futures_zero-0.0b11.dist-info/METADATA
futures_zero-0.0b11.dist-info/WHEEL
futures_zero-0.0b11.dist-info/top_level.txt
futures_zero-0.0b11.dist-info/RECORD
